[
  {
    "page": 1,
    "cells": [
      {
        "r": 0,
        "c": 0,
        "name": "NL SEALE J",
        "raw": "B NL ) SEALE J PANINI"
      },
      {
        "r": 0,
        "c": 1,
        "name": "-",
        "raw": "- (0) N RIDLE BAKU 8-4-1998 I 1.76 79K ET TTT 3"
      },
      {
        "r": 0,
        "c": 2,
        "name": "V",
        "raw": "A V4 - SERGE GNABRY 14-7-1985 1 1.76 M I 75K"
      },
      {
        "r": 0,
        "c": 3,
        "name": "NE",
        "raw": "E NE 3-6-2003 L77 71"
      },
      {
        "r": 1,
        "c": 0,
        "name": "ANTONIO RUDIGER",
        "raw": "ANTONIO RUDIGER 3-3-1993 1.90 85K REAL MADRID CF (ESP)"
      },
      {
        "r": 1,
        "c": 1,
        "name": "FELIX NMECHA",
        "raw": "A FELIX NMECHA 10-10-2000 1.98 73K"
      },
      {
        "r": 1,
        "c": 2,
        "name": "NY ' TYE B- NY NICO SCHLOTTERBECK",
        "raw": "NY ' TYE B- NY NICO SCHLOTTERBECK 112-1999 191 I 86 BORUSSIA DORTMUND (GER) B LLY"
      },
      {
        "r": 1,
        "c": 3,
        "name": "EE. NICK WOLTEMADE",
        "raw": "EE. NICK WOLTEMADE 5 14-2-2002 1.98 90 K NEWCASTLE UNITED FC (ENG) BEELER"
      },
      {
        "r": 2,
        "c": 0,
        "name": "MAXIMILIAN MITTELSTADT",
        "raw": "MAXIMILIAN MITTELSTADT 18-3-1997 1.89 M T1K VFBSTUTTGART (GER) 8 ZV TEE"
      },
      {
        "r": 2,
        "c": 1,
        "name": "MARC-ANDRE TER STEGEN",
        "raw": "MARC-ANDRE TER STEGEN 30-4-1992 1.87 I 85K (FCBARCELONA(ESP BEL ILD"
      },
      {
        "r": 2,
        "c": 2,
        "name": "JAMAL MUSIALA",
        "raw": "JAMAL MUSIALA 26-2-2003 1.86 M 75 K SER S"
      },
      {
        "r": 2,
        "c": 3,
        "name": "NF LEON GORETZKA",
        "raw": "NF LEON GORETZKA 6-2-1995 1 1.89 M 79K"
      },
      {
        "r": 3,
        "c": 0,
        "name": "HAVEN",
        "raw": "A HAVEN 116-1999 193 I 82K ARSENAL FC (ENG) EXIT"
      },
      {
        "r": 3,
        "c": 1,
        "name": "",
        "raw": "11-21996 195 94 K FC BAYERN MUNCHEN (GER)"
      },
      {
        "r": 3,
        "c": 2,
        "name": "",
        "raw": "9-5-2000 178 M I 61 VFLWOLFSBURG (GER) BET VI HY"
      },
      {
        "r": 3,
        "c": 3,
        "name": "",
        "raw": "29-1-1994 1.70 M 66 K 1. FSV MAINZ 05 (GER)"
      }
    ]
  }
]